darty/__init__.py
darty/dependency_manager.py
darty/output_writer.py
darty/settings.py
darty/utils.py
darty/commands/__init__.py
darty/commands/abstract.py
darty/commands/configure.py
darty/commands/download.py
darty/commands/publish.py
darty/commands/publish_local.py
darty/commands/update.py
darty/drivers/__init__.py
darty/drivers/abstract.py
darty/drivers/factory.py
darty/drivers/s3/__init__.py
darty/drivers/s3/files/__init__.py
darty/drivers/s3/files/driver.py
darty/drivers/s3/files/utils.py
darty/drivers/s3/zip/__init__.py
darty/drivers/s3/zip/driver.py
darty/drivers/s3/zip/utils.py
darty/drivers/test/__init__.py
darty/drivers/test/driver.py
darty/helpers/__init__.py
darty/helpers/commands.py
darty/helpers/validation.py
darty/package/__init__.py
darty/package/dependency.py
darty/package/package_info.py
darty/package/repository.py
darty/package/validators.py
darty-1.0.1.data/scripts/darty
darty-1.0.1.dist-info/DESCRIPTION.rst
darty-1.0.1.dist-info/METADATA
darty-1.0.1.dist-info/RECORD
darty-1.0.1.dist-info/WHEEL
darty-1.0.1.dist-info/entry_points.txt
darty-1.0.1.dist-info/metadata.json
darty-1.0.1.dist-info/top_level.txt
