Metadata-Version: 2.0
Name: darty
Version: 1.0.1
Summary: Data Dependency Manager
Home-page: UNKNOWN
Author: UNKNOWN
Author-email: UNKNOWN
License: UNKNOWN
Platform: UNKNOWN
Requires-Dist: boto3
Requires-Dist: schema
